dyff/client/__init__.py
dyff/client/_apigroups.py
dyff/client/_inference.py
dyff/client/_version.py
dyff/client/auth.py
dyff/client/client.py
dyff/client/errors.py
dyff/client/http.py
dyff/client/ops.py
dyff/client/raw.py
dyff_client-0.23.13.dist-info/licenses/LICENSE
dyff_client-0.23.13.dist-info/licenses/NOTICE
dyff_client-0.23.13.dist-info/METADATA
dyff_client-0.23.13.dist-info/WHEEL
dyff_client-0.23.13.dist-info/top_level.txt
dyff_client-0.23.13.dist-info/RECORD
