Metadata-Version: 2.4
Name: dyff-client
Version: 0.23.13
Summary: Python client for the Dyff AI auditing platform.
Author-email: Digital Safety Research Institute <contact@dsri.org>
License: Apache-2.0
Project-URL: Home, https://gitlab.com/dyff/packages/dyff-client
Project-URL: Issues, https://gitlab.com/dyff/packages/dyff-client/-/issues
Keywords: ai,audit,safety,evaluation
Classifier: Development Status :: 3 - Alpha
Classifier: Intended Audience :: Science/Research
Classifier: License :: OSI Approved :: Apache Software License
Classifier: Operating System :: OS Independent
Classifier: Programming Language :: Python :: 3
Classifier: Programming Language :: Python :: 3.10
Classifier: Programming Language :: Python :: 3.11
Classifier: Programming Language :: Python :: 3.12
Classifier: Topic :: Scientific/Engineering :: Artificial Intelligence
Requires-Python: >=3.10
License-File: LICENSE
License-File: NOTICE
Requires-Dist: absl-py
Requires-Dist: azure-core
Requires-Dist: dyff-schema>=0.39.3
Requires-Dist: httpx
Requires-Dist: isodate
Requires-Dist: jsonpath-ng
Requires-Dist: numpy<2
Requires-Dist: pandas
Requires-Dist: pyarrow
Requires-Dist: pydantic<3.0.0,>=2.0.0
Requires-Dist: tqdm
Requires-Dist: websockets
Dynamic: license-file
